spectra/__init__.py
spectra/_version.py
spectra/core.py
spectra/grapefruit.py
spectra-0.1.0.dist-info/LICENSE.txt
spectra-0.1.0.dist-info/METADATA
spectra-0.1.0.dist-info/WHEEL
spectra-0.1.0.dist-info/namespace_packages.txt
spectra-0.1.0.dist-info/top_level.txt
spectra-0.1.0.dist-info/RECORD
