Metadata-Version: 2.2
Name: spectra
Version: 0.1.0
Summary: Color scales and color conversion made easy for Python.
Home-page: http://github.com/jsvine/spectra
Author: Jeremy Singer-Vine
Author-email: jsvine@gmail.com
License: MIT
Keywords: color colors colorspace scale spectrum
Classifier: Development Status :: 3 - Alpha
Classifier: Intended Audience :: Developers
Classifier: License :: OSI Approved :: MIT License
Classifier: Operating System :: OS Independent
Classifier: Programming Language :: Python :: 2.7
Classifier: Programming Language :: Python :: 3.1
Classifier: Programming Language :: Python :: 3.4
Classifier: Programming Language :: Python :: 3.5
Classifier: Programming Language :: Python :: 3.6
License-File: LICENSE.txt
Requires-Dist: colormath2>=3.0.0
Dynamic: author
Dynamic: author-email
Dynamic: classifier
Dynamic: home-page
Dynamic: keywords
Dynamic: license
Dynamic: requires-dist
Dynamic: summary
